.gitignore
CHANGES.txt
LICENSE.txt
MANIFEST.in
README.rst
setup.py
CodeKitLang.egg-info/PKG-INFO
CodeKitLang.egg-info/SOURCES.txt
CodeKitLang.egg-info/dependency_links.txt
CodeKitLang.egg-info/entry_points.txt
CodeKitLang.egg-info/not-zip-safe
CodeKitLang.egg-info/requires.txt
CodeKitLang.egg-info/top_level.txt
codekitlang/__init__.py
codekitlang/command.py
codekitlang/compiler.py
codekitlang/tests/__init__.py
codekitlang/tests/test_command.py
codekitlang/tests/test_compiler.py
codekitlang/tests/data/b/_file3.kit
codekitlang/tests/data/b/file1.html
codekitlang/tests/data/b/file2.kit
codekitlang/tests/data/b/generate_to_str_cyclic_inclusion1.kit
codekitlang/tests/data/b/generate_to_str_cyclic_inclusion2a.kit
codekitlang/tests/data/b/generate_to_str_cyclic_inclusion2b.kit
codekitlang/tests/data/b/generate_to_str_missing_var.kit
codekitlang/tests/data/b/parse_file_missing_file.kit
codekitlang/tests/data/b/parse_file_test2.html
codekitlang/tests/data/b/parse_file_test3.kit
codekitlang/tests/data/b/parse_unicode.kit
codekitlang/tests/data/b/unicode_input.html
codekitlang/tests/data/b/sub/_file6.kit
codekitlang/tests/data/b/sub/file4.html
codekitlang/tests/data/b/sub/file5.kit
codekitlang/tests/data/d/parse_unicode_result.html
codekitlang/tests/data/d/dd/parse_file_test3.html
codekitlang/tests/data/f1/_file9.kit
codekitlang/tests/data/f1/file7.html
codekitlang/tests/data/f1/file8.kit
codekitlang/tests/data/f1/sub/_file12.kit
codekitlang/tests/data/f1/sub/file10.html
codekitlang/tests/data/f1/sub/file11.kit
codekitlang/tests/data/f2/_file15.kit
codekitlang/tests/data/f2/file13.html
codekitlang/tests/data/f2/file14.kit