Metadata-Version: 1.1
Name: CodeKitLang
Version: 0.4
Summary: CodeKit Language Compiler, Python implementation
Home-page: https://github.com/gjo/python-codekitlang
Author: OCHIAI, Gouji
Author-email: gjo.ext@gmail.com
License: BSD
Platform: UNKNOWN
Classifier: Environment :: Console
Classifier: Intended Audience :: Developers
Classifier: License :: OSI Approved :: BSD License
Classifier: Programming Language :: Python
Classifier: Programming Language :: Python :: 2.7
Classifier: Topic :: Internet :: WWW/HTTP :: Site Management
Classifier: Topic :: Software Development :: Code Generators
Classifier: Topic :: Text Processing :: Markup :: HTML
